LAB9/Johnson_4Bit.v
module johnson_counter_4bit (
    input clk,
    input rst,
    output reg [3:0] q
);
    always @(posedge clk or posedge rst) begin
        if (rst)
            q <= 4'b0000;                // start with all zeros
        else
            q <= {~q[0], q[3:1]};        // twisted feedback
    end
endmodule

LAB9/tb_Johnson_4Bit.v
`timescale 1ns/1ps
module tb_johnson_counter_4bit;
    reg clk, rst;
    wire [3:0] q;

    johnson_counter_4bit uut (.clk(clk), .rst(rst), .q(q));

    always #5 clk = ~clk;

    initial begin
        $dumpfile("waves.vcd");
        $dumpvars(1, tb_johnson_counter_4bit);

        clk = 0; rst = 1;
        #10 rst = 0;

        #200;
        $finish;
    end
endmodule

LAB9/waves.vcd
$date
	Mon Nov 10 10:52:55 2025
$end
$version
	Icarus Verilog
$end
$timescale
	1ps
$end
$scope module tb_johnson_counter_4bit $end
$var wire 4 ! q [3:0] $end
$var reg 1 " clk $end
$var reg 1 # rst $end
$upscope $end
$enddefinitions $end
$comment Show the parameter values. $end
$dumpall
$end
#0
$dumpvars
1#
0"
b0 !
$end
#5000
1"
#10000
0"
0#
#15000
b1000 !
1"
#20000
0"
#25000
b1100 !
1"
#30000
0"
#35000
b1110 !
1"
#40000
0"
#45000
b1111 !
1"
#50000
0"
#55000
b111 !
1"
#60000
0"
#65000
b11 !
1"
#70000
0"
#75000
b1 !
1"
#80000
0"
#85000
b0 !
1"
#90000
0"
#95000
b1000 !
1"
#100000
0"
#105000
b1100 !
1"
#110000
0"
#115000
b1110 !
1"
#120000
0"
#125000
b1111 !
1"
#130000
0"
#135000
b111 !
1"
#140000
0"
#145000
b11 !
1"
#150000
0"
#155000
b1 !
1"
#160000
0"
#165000
b0 !
1"
#170000
0"
#175000
b1000 !
1"
#180000
0"
#185000
b1100 !
1"
#190000
0"
#195000
b1110 !
1"
#200000
0"
#205000
b1111 !
1"
