LAB9/Ripple_2Bit.v
module ripple_counter_2bit (
    input clk,
    input rst,
    output reg [1:0] q
);
    always @(posedge clk or posedge rst) begin
        if (rst)
            q <= 2'b00;
        else begin
            q[0] <= ~q[0];           
            q[1] <= q[1] ^ q[0];     
        end
    end
endmodule

LAB9/tb_Ripple_2Bit.v
`timescale 1ns/1ps
module tb_ripple_counter_2bit;
    reg clk, rst;
    wire [1:0] q;

    ripple_counter_2bit uut (.clk(clk), .rst(rst), .q(q));

    
    always #5 clk = ~clk;

    initial begin
        $dumpfile("waves.vcd");
        $dumpvars(1, tb_ripple_counter_2bit);   

        clk = 0; rst = 1;
        #10 rst = 0;

        #100;  
        $finish;
    end
endmodule

LAB9/waves.vcd
$date
	Mon Nov 10 11:39:18 2025
$end
$version
	Icarus Verilog
$end
$timescale
	1ps
$end
$scope module tb_ripple_counter_2bit $end
$var wire 2 ! q [1:0] $end
$var reg 1 " clk $end
$var reg 1 # rst $end
$upscope $end
$enddefinitions $end
$comment Show the parameter values. $end
$dumpall
$end
#0
$dumpvars
1#
0"
b0 !
$end
#5000
1"
#10000
0"
0#
#15000
b1 !
1"
#20000
0"
#25000
b10 !
1"
#30000
0"
#35000
b11 !
1"
#40000
0"
#45000
b0 !
1"
#50000
0"
#55000
b1 !
1"
#60000
0"
#65000
b10 !
1"
#70000
0"
#75000
b11 !
1"
#80000
0"
#85000
b0 !
1"
#90000
0"
#95000
b1 !
1"
#100000
0"
#105000
b10 !
1"
