LAB8/PISO.v
module PISO (
    input clk,
    input rst,
    input load,               // 1 = load parallel data, 0 = shift
    input [3:0] parallel_in,
    output serial_out
);
    reg [3:0] shift_reg;

    always @(posedge clk or posedge rst) begin
        if (rst)
            shift_reg <= 4'b0000;
        else if (load)
            shift_reg <= parallel_in;                 // load data
        else
            shift_reg <= {shift_reg[2:0], 1'b0};      // shift left
    end

    assign serial_out = shift_reg[3]; // MSB output
endmodule

LAB8/tb_PISO.v
`timescale 1ns/1ps
module tb_PISO;
    reg clk, rst, load;
    reg [3:0] parallel_in;
    wire serial_out;

    PISO uut (.clk(clk), .rst(rst), .load(load), .parallel_in(parallel_in), .serial_out(serial_out));

    always #5 clk = ~clk;

    initial begin
        $dumpfile("waves.vcd");
        $dumpvars(0, tb_PISO);

        clk = 0; rst = 1; load = 0; parallel_in = 4'b0000;
        #10 rst = 0;

        // Load parallel data
        load = 1; parallel_in = 4'b1011; #10;
        load = 0;

        // Shift out serially
        #50;

        $finish;
    end
endmodule

LAB8/waves.vcd
$date
	Mon Nov 10 02:45:02 2025
$end
$version
	Icarus Verilog
$end
$timescale
	1ps
$end
$scope module tb_PISO $end
$var wire 1 ! serial_out $end
$var reg 1 " clk $end
$var reg 1 # load $end
$var reg 4 $ parallel_in [3:0] $end
$var reg 1 % rst $end
$scope module uut $end
$var wire 1 " clk $end
$var wire 1 # load $end
$var wire 4 & parallel_in [3:0] $end
$var wire 1 % rst $end
$var wire 1 ! serial_out $end
$var reg 4 ' shift_reg [3:0] $end
$upscope $end
$upscope $end
$enddefinitions $end
$comment Show the parameter values. $end
$dumpall
$end
#0
$dumpvars
b0 '
b0 &
1%
b0 $
0#
0"
0!
$end
#5000
1"
#10000
0"
b1011 $
b1011 &
1#
0%
#15000
1!
b1011 '
1"
#20000
0"
0#
#25000
0!
b110 '
1"
#30000
0"
#35000
1!
b1100 '
1"
#40000
0"
#45000
b1000 '
1"
#50000
0"
#55000
0!
b0 '
1"
