LAB5/demux.v
module demux(

    input wire input_wire,
    input wire A0,A1,A2,
    output wire Y0,Y1,Y2,Y3,Y4,Y5,Y6,Y7

);

assign Y0 = (A2 == 0 && A1 == 0 && A0 == 0) ? input_wire : 0 ;
assign Y1 = (A2 == 0 && A1 == 0 && A0 == 1) ? input_wire : 0 ;
assign Y2 = (A2 == 0 && A1 == 1 && A0 == 0) ? input_wire : 0 ;
assign Y3 = (A2 == 0 && A1 == 1 && A0 == 1) ? input_wire : 0 ;
assign Y4 = (A2 == 1 && A1 == 0 && A0 == 0) ? input_wire : 0 ;
assign Y5 = (A2 == 1 && A1 == 0 && A0 == 1) ? input_wire : 0 ;
assign Y6 = (A2 == 1 && A1 == 1 && A0 == 0) ? input_wire : 0 ;
assign Y7 = (A2 == 1 && A1 == 1 && A0 == 1) ? input_wire : 0 ;

endmodule

LAB5/tb_demux.v

`timescale 1ps/1ps

module tb_demux;

    reg input_wire;
    reg A0, A1, A2;
    wire Y0, Y1, Y2, Y3, Y4, Y5, Y6, Y7;

    
    demux uut (
        .input_wire(input_wire),
        .A0(A0), .A1(A1), .A2(A2),
        .Y0(Y0), .Y1(Y1), .Y2(Y2), .Y3(Y3),
        .Y4(Y4), .Y5(Y5), .Y6(Y6), .Y7(Y7)
    );

    initial begin
        
        $dumpfile("wave.vcd");
        $dumpvars(0, tb_demux);
        
        input_wire = 1; 

        $display("Time | A2 A1 A0 | Y0 Y1 Y2 Y3 Y4 Y5 Y6 Y7");

        A2=0; A1=0; A0=0; #10;
        A2=0; A1=0; A0=1; #10;
        A2=0; A1=1; A0=0; #10;
        A2=0; A1=1; A0=1; #10;
        A2=1; A1=0; A0=0; #10;
        A2=1; A1=0; A0=1; #10;
        A2=1; A1=1; A0=0; #10;
        A2=1; A1=1; A0=1; #10;

        $finish;
    end

    initial begin
        $monitor("%4t |  %b  %b  %b  |  %b  %b  %b  %b  %b  %b  %b  %b", 
                 $time, A2, A1, A0, Y0, Y1, Y2, Y3, Y4, Y5, Y6, Y7);
    end

endmodule

LAB5/wave.vcd
$date
	Mon Sep 22 11:26:20 2025
$end
$version
	Icarus Verilog
$end
$timescale
	1ps
$end
$scope module tb_demux $end
$var wire 1 ! Y7 $end
$var wire 1 " Y6 $end
$var wire 1 # Y5 $end
$var wire 1 $ Y4 $end
$var wire 1 % Y3 $end
$var wire 1 & Y2 $end
$var wire 1 ' Y1 $end
$var wire 1 ( Y0 $end
$var reg 1 ) A0 $end
$var reg 1 * A1 $end
$var reg 1 + A2 $end
$var reg 1 , input_wire $end
$scope module uut $end
$var wire 1 ) A0 $end
$var wire 1 * A1 $end
$var wire 1 + A2 $end
$var wire 1 , input_wire $end
$var wire 1 ! Y7 $end
$var wire 1 " Y6 $end
$var wire 1 # Y5 $end
$var wire 1 $ Y4 $end
$var wire 1 % Y3 $end
$var wire 1 & Y2 $end
$var wire 1 ' Y1 $end
$var wire 1 ( Y0 $end
$upscope $end
$upscope $end
$enddefinitions $end
$comment Show the parameter values. $end
$dumpall
$end
#0
$dumpvars
1,
0+
0*
0)
1(
0'
0&
0%
0$
0#
0"
0!
$end
#10
0(
1'
1)
#20
0'
1&
0)
1*
#30
0&
1%
1)
#40
0%
1$
0)
0*
1+
#50
0$
1#
1)
#60
0#
1"
0)
1*
#70
0"
1!
1)
