LAB3/full_adder_nand.v
module full_adder_nand (
    input a, b, cin,
    output sum, carry
);
    wire n1, n2, n3, n4, n5, n6, n7, n8;

    // First XOR (a ⊕ b)
    nand (n1, a, b);
    nand (n2, a, n1);
    nand (n3, b, n1);
    nand (n4, n2, n3);   // n4 = a ⊕ b

    // Second XOR (n4 ⊕ cin) → SUM
    nand (n5, n4, cin);
    nand (n6, n4, n5);
    nand (n7, cin, n5);
    nand (sum, n6, n7);  // SUM output

    // Carry = (a·b) + (cin·(a⊕b))
    nand (n8, n1, n5);   // OR equivalent with NANDs
    nand (carry, n8, n8);
endmodule

LAB3/tb_full_adder_nand.v
`timescale 1ns/1ps
module tb_full_adder_nand;
    reg a, b, cin;
    wire sum, carry;

    // Instantiate NAND Full Adder
    full_adder_nand uut (
        .a(a),
        .b(b),
        .cin(cin),
        .sum(sum),
        .carry(carry)
    );

    initial begin
        $dumpfile("waves.vcd");
        $dumpvars(0, tb_full_adder_nand);

        $display("Time | A B Cin | SUM CARRY");

        // Test all 8 input combinations
        a=0; b=0; cin=0; #10;
        a=0; b=0; cin=1; #10;
        a=0; b=1; cin=0; #10;
        a=0; b=1; cin=1; #10;
        a=1; b=0; cin=0; #10;
        a=1; b=0; cin=1; #10;
        a=1; b=1; cin=0; #10;
        a=1; b=1; cin=1; #10;

        $finish;
    end

    initial begin
        $monitor("%4t | %b %b  %b  |  %b    %b", $time, a, b, cin, sum, carry);
    end
endmodule

LAB3/waves.vcd
$date
	Mon Nov 10 10:57:15 2025
$end
$version
	Icarus Verilog
$end
$timescale
	1ps
$end
$scope module tb_full_adder_nand $end
$var wire 1 ! sum $end
$var wire 1 " carry $end
$var reg 1 # a $end
$var reg 1 $ b $end
$var reg 1 % cin $end
$scope module uut $end
$var wire 1 # a $end
$var wire 1 $ b $end
$var wire 1 " carry $end
$var wire 1 % cin $end
$var wire 1 & n1 $end
$var wire 1 ' n2 $end
$var wire 1 ( n3 $end
$var wire 1 ) n4 $end
$var wire 1 * n5 $end
$var wire 1 + n6 $end
$var wire 1 , n7 $end
$var wire 1 - n8 $end
$var wire 1 ! sum $end
$upscope $end
$upscope $end
$enddefinitions $end
$comment Show the parameter values. $end
$dumpall
$end
#0
$dumpvars
0-
1,
1+
1*
0)
1(
1'
1&
0%
0$
0#
1"
0!
$end
#10000
1!
0,
1%
#20000
0+
1!
1)
1,
0(
0%
1$
#30000
0!
0"
1+
1-
0*
1,
1%
#40000
1!
1"
0+
0-
1*
1(
0'
0%
0$
1#
#50000
0!
0"
1+
1-
0*
1,
1%
#60000
0!
0)
1+
1'
1*
0&
1(
0%
1$
#70000
1!
0,
1%
