LAB3/full_adder.v
module full_adder (
    input a, b, cin,
    output sum, cout
);
    wire xor1, and1, and2;

    assign xor1 = a ^ b;
    assign sum  = xor1 ^ cin;
    assign and1 = a & b;
    assign and2 = cin & xor1;
    assign cout = and1 | and2;

endmodule

LAB3/tb_full_adder.v
`timescale 1ns/1ps
module tb_full_adder;

    reg a, b, cin;
    wire sum, cout;

    // Instantiate Full Adder
    full_adder uut (
        .a(a),
        .b(b),
        .cin(cin),
        .sum(sum),
        .cout(cout)
    );

    initial begin
        $dumpfile("wave.vcd");
        $dumpvars(0, tb_full_adder);

        $display("Time | A B Cin | Sum Cout");

        // Test all 8 cases
        a=0; b=0; cin=0; #10;
        a=0; b=0; cin=1; #10;
        a=0; b=1; cin=0; #10;
        a=0; b=1; cin=1; #10;
        a=1; b=0; cin=0; #10;
        a=1; b=0; cin=1; #10;
        a=1; b=1; cin=0; #10;
        a=1; b=1; cin=1; #10;

        $finish;
    end

    initial begin
        $monitor("%4t | %b %b  %b  |  %b    %b", 
                 $time, a, b, cin, sum, cout);
    end

endmodule

LAB3/wave.vcd
$date
	Mon Sep 08 00:45:34 2025
$end
$version
	Icarus Verilog
$end
$timescale
	1ps
$end
$scope module tb_full_adder $end
$var wire 1 ! sum $end
$var wire 1 " cout $end
$var reg 1 # a $end
$var reg 1 $ b $end
$var reg 1 % cin $end
$scope module uut $end
$var wire 1 # a $end
$var wire 1 & and1 $end
$var wire 1 ' and2 $end
$var wire 1 $ b $end
$var wire 1 % cin $end
$var wire 1 " cout $end
$var wire 1 ! sum $end
$var wire 1 ( xor1 $end
$upscope $end
$upscope $end
$enddefinitions $end
$comment Show the parameter values. $end
$dumpall
$end
#0
$dumpvars
0(
0'
0&
0%
0$
0#
0"
0!
$end
#10000
1!
1%
#20000
1(
0%
1$
#30000
1"
0!
1'
1%
#40000
0"
1!
0'
0%
0$
1#
#50000
1"
0!
1'
1%
#60000
0'
0(
1&
0%
1$
#70000
1!
1%
