LAB7/JK_Flip_Flop.v

module JK_Flip_Flop (
    input J, K, clk, reset,
    output reg Q
);

always @(posedge clk or posedge reset) begin
    if (reset)
        Q <= 0;                     
    else begin
        case ({J, K})
            2'b00: Q <= Q;          
            2'b01: Q <= 0;          
            2'b10: Q <= 1;          
            2'b11: Q <= ~Q;         
        endcase
    end
end

endmodule

LAB7/tb_JK_Flip_Flop.v
`timescale 1ns / 1ps
module JK_Flip_Flop_tb;


reg J, K, clk, reset;
wire Q;


JK_Flip_Flop uut (
    .J(J),
    .K(K),
    .clk(clk),
    .reset(reset),
    .Q(Q)
);


always #5 clk = ~clk;

initial begin

    $dumpfile("waves.vcd");
    $dumpvars(0, JK_Flip_Flop_tb);
    
    clk = 0;
    reset = 1;
    J = 0;
    K = 0;

    
    #10 reset = 0;

    
    #10 J = 0; K = 0;  
    #10 J = 0; K = 1;  
    #10 J = 1; K = 0;  
    #10 J = 1; K = 1;  
    #10 J = 1; K = 1;  
    #10 J = 0; K = 1;  

    
    #10 $finish;
end


initial begin

    $monitor("| clk=%b | J=%b | K=%b | Q=%b |", 
               clk, J, K, Q);
end

endmodule

LAB7/waves.vcd
$date
	Mon Oct 13 11:04:52 2025
$end
$version
	Icarus Verilog
$end
$timescale
	1ps
$end
$scope module JK_Flip_Flop_tb $end
$var wire 1 ! Q $end
$var reg 1 " J $end
$var reg 1 # K $end
$var reg 1 $ clk $end
$var reg 1 % reset $end
$scope module uut $end
$var wire 1 " J $end
$var wire 1 # K $end
$var wire 1 $ clk $end
$var wire 1 % reset $end
$var reg 1 ! Q $end
$upscope $end
$upscope $end
$enddefinitions $end
$comment Show the parameter values. $end
$dumpall
$end
#0
$dumpvars
1%
0$
0#
0"
0!
$end
#5000
1$
#10000
0$
0%
#15000
1$
#20000
0$
#25000
1$
#30000
0$
1#
#35000
1$
#40000
0$
0#
1"
#45000
1!
1$
#50000
0$
1#
#55000
0!
1$
#60000
0$
#65000
1!
1$
#70000
0$
0"
#75000
0!
1$
